msproject/__init__.py
msproject/ActualStartDrivers/__init__.py
msproject/Application/__init__.py
msproject/Assignment/__init__.py
msproject/Assignments/__init__.py
msproject/Availabilities/__init__.py
msproject/Availability/__init__.py
msproject/Calendar/__init__.py
msproject/CalendarDrivers/__init__.py
msproject/Calendars/__init__.py
msproject/Cell/__init__.py
msproject/Chart/__init__.py
msproject/ChildDrivers/__init__.py
msproject/CodeMask/__init__.py
msproject/CodeMaskLevel/__init__.py
msproject/CostRateTable/__init__.py
msproject/CostRateTables/__init__.py
msproject/Day/__init__.py
msproject/Days/__init__.py
msproject/Engagement/__init__.py
msproject/EngagementComment/__init__.py
msproject/EngagementComments/__init__.py
msproject/Engagements/__init__.py
msproject/EventInfo/__init__.py
msproject/Exception/__init__.py
msproject/Exceptions/__init__.py
msproject/Filter/__init__.py
msproject/Filters/__init__.py
msproject/Group/__init__.py
msproject/Group2/__init__.py
msproject/GroupCriteria/__init__.py
msproject/GroupCriteria2/__init__.py
msproject/GroupCriterion/__init__.py
msproject/GroupCriterion2/__init__.py
msproject/Groups/__init__.py
msproject/Groups2/__init__.py
msproject/List/__init__.py
msproject/LookupTable/__init__.py
msproject/LookupTableEntry/__init__.py
msproject/Month/__init__.py
msproject/Months/__init__.py
msproject/OutlineCode/__init__.py
msproject/OutlineCodes/__init__.py
msproject/OverAllocatedAssignments/__init__.py
msproject/Pane/__init__.py
msproject/PayRate/__init__.py
msproject/PayRates/__init__.py
msproject/Period/__init__.py
msproject/PredecessorDrivers/__init__.py
msproject/Profile/__init__.py
msproject/Profiles/__init__.py
msproject/Project/__init__.py
msproject/Projects/__init__.py
msproject/Report/__init__.py
msproject/Reports/__init__.py
msproject/ReportTable/__init__.py
msproject/ReportTemplate/__init__.py
msproject/ReportTemplates/__init__.py
msproject/Resource/__init__.py
msproject/ResourceGroups/__init__.py
msproject-0.1.1.dist-info/METADATA
msproject-0.1.1.dist-info/WHEEL
msproject-0.1.1.dist-info/RECORD
